{
	"author": ["Shin Gyu Kim", "Hyuck Han", "Kyungho Jeon", "Hyungsoo Jung", "Heon Young Yeom"],
	"booktitle": "Proceedings of the 24th Symposium on Applied Computing",
	"booktitleshort": "SAC",
	"crossref": "conf/sac/2009",
	"dblpkey": "conf/sac/KimHJJY09",
	"doi": "10.1145/1529282.1529694",
	"editor": ["Sung Y. Shin", "Sascha Ossowski"],
	"ee": "http://doi.acm.org/10.1145/1529282.1529694",
	"isbn": "978-1-60558-166-8",
	"pages": "1841-1842",
	"publisher": "ACM",
	"stemmed": ["visual", "inform", "flow", "veri", "larg", "social", "network"],
	"tag": ["data flow", "network", "scalability", "social", "visualisation"],
	"title": "Visualization of information flows in a very large social network",
	"type": "inproceedings",
	"venue": "SAC",
	"year": 2009
}