{
	"author": ["Feng Tian", "Fei Lv", "Jingtao Wang", "Hongan Wang", "Wencan Luo", "Matthew Kam", "Vidya Setlur", "Guozhong Dai", "John Canny"],
	"booktitle": "CHI",
	"crossref": "conf/chi/2010",
	"dblpkey": "conf/chi/TianLWWLKSDC10",
	"ee": "http://doi.acm.org/10.1145/1753326.1753565",
	"pages": "1603-1612",
	"title": "Let's play chinese characters: mobile learning approaches via culturally inspired group games",
	"type": "inproceedings",
	"url": "db/conf/chi/chi2010.html#TianLWWLKSDC10",
	"year": "2010"
}
