{
	"author": ["Guo Li", "Haiyi Zhu", "Tun Lu", "Xianghua Ding", "Ning Gu"],
	"booktitle": "CSCW",
	"crossref": "conf/cscw/2015",
	"dblpkey": "conf/cscw/LiZLDG15",
	"doi": "10.1145/2675133.2675155",
	"ee": "http://doi.acm.org/10.1145/2675133.2675155",
	"pages": "1080-1091",
	"publisher": "ACM",
	"tag": ["collaboration", "editing", "wiki"],
	"title": "Is It Good to Be Like Wikipedia?: Exploring the Trade-offs of Introducing Collaborative Editing Model to Q&A Sites",
	"type": "inproceedings",
	"venue": "CSCW",
	"year": 2015
}