{
	"author": ["Igor Chalas", "Zuzana Ferkova", "Katarína Furmanová", "Jiri Sochor", "Barbora Kozlíková"],
	"booktitle": "Proceedings of the Seventh International Conference on Games and Virtual Worlds for Serious Applications",
	"booktitleshort": "VS-Games",
	"crossref": "conf/vsgames/2015",
	"dblpkey": "conf/vsgames/ChalasFFSK15",
	"doi": "10.1109/VS-GAMES.2015.7295777",
	"isbn": "978-1-4799-8102-1",
	"pages": "1-8",
	"publisher": "IEEE Computer Society",
	"stemmed": ["generat", "of", "variabl", "human", "face", "from", "d", "scan", "dataset"],
	"tag": ["3d", "dataset", "generative"],
	"title": "Generation of Variable Human Faces from 3D Scan Dataset",
	"type": "inproceedings",
	"venue": "CoG",
	"year": 2015
}