{
	"author": ["David S. Doermann", "Huiping Li", "Omid E. Kia"],
	"booktitle": "Proceedings of the Fourth International Conference on Document Analysis and Recognition",
	"booktitleshort": "ICDAR",
	"crossref": "conf/icdar/1997",
	"dblpkey": "conf/icdar/DoermannLK97",
	"doi": "10.1109/ICDAR.1997.619863",
	"ee": "http://doi.ieeecomputersociety.org/10.1109/ICDAR.1997.619863",
	"isbn": "0-8186-7898-4",
	"pages": "314-318",
	"publisher": "IEEE Computer Society",
	"publishershort": "IEEE CS",
	"stemmed": ["the", "detect", "of", "duplic", "in", "document", "imag", "databas"],
	"tag": ["database", "detection", "documentation", "image"],
	"title": "The Detection of Duplicates in Document Image Databases",
	"type": "inproceedings",
	"venue": "ICDAR",
	"year": 1997
}