{
	"author": [
		"Xuejun Zhao",
		"Xinyu Liu",
		"Shengling Zheng",
		"Baochang Pan",
		"Yuan Yan Tang"
	],
	"booktitle": "Proceedings of the Fourth International Conference on Document Analysis and Recognition",
	"booktitleshort": "ICDAR",
	"crossref": "conf/icdar/1997",
	"dblpkey": "conf/icdar/ZhaoLZPT97",
	"doi": "10.1109/ICDAR.1997.620585",
	"ee": [
		"http://dx.doi.org/10.1109/ICDAR.1997.620585",
		"http://doi.ieeecomputersociety.org/10.1109/ICDAR.1997.620585"
	],
	"pages": "645-648",
	"publisher": "IEEE Computer Society",
	"publishershort": "IEEE CS",
	"stemmed": [
		"on",
		"line",
		"recognit",
		"handwritten",
		"mathemat",
		"symbol"
	],
	"tag": [
		"online",
		"recognition"
	],
	"title": "On-line recognition handwritten mathematical symbol",
	"type": "inproceedings",
	"venue": "ICDAR",
	"year": 1997
}