{
	"author": ["Pengcheng Huang", "Hoeseok Yang", "Lothar Thiele"],
	"booktitle": "DAC",
	"crossref": "conf/dac/2014",
	"dblpkey": "conf/dac/HuangYT14",
	"doi": "10.1145/2593069.2593169",
	"ee": "http://doi.acm.org/10.1145/2593069.2593169",
	"pages": "131:1-131:6",
	"publisher": "ACM",
	"stemmed": ["on", "the", "schedul", "of", "fault", "toler", "mix", "critic", "system"],
	"tag": ["fault tolerance", "on the", "scheduling"],
	"title": "On the Scheduling of Fault-Tolerant Mixed-Criticality Systems",
	"type": "inproceedings",
	"venue": "DAC",
	"year": 2014
}