{
	"booktitle": "CGO",
	"dblpkey": "conf/cgo/2007",
	"ee": ["http://ieeexplore.ieee.org/xpl/mostRecentIssue.jsp?punumber=4145089", "http://www.computer.org/csdl/proceedings/cgo/2007/2764/00/index.html", "http://dl.acm.org/citation.cfm?id=1251974"],
	"isbn": "978-0-7695-2764-2",
	"publisher": "IEEE Computer Society",
	"title": "Fifth International Symposium on Code Generation and Optimization (CGO 2007), 11-14 March 2007, San Jose, California, USA",
	"type": "proceedings",
	"url": "db/conf/cgo/cgo2007.html",
	"year": "2007"
}
