{
	"author": ["Andrew L. Rukhin", "Patrick Grother", "P. Jonathon Phillips", "Stefan Leigh", "Alan Heckert", "Elaine M. Newton"],
	"booktitle": "ICPR (2)",
	"crossref": "conf/icpr/2002",
	"dblpkey": "conf/icpr/RukhinGPLHN02",
	"ee": ["http://dx.doi.org/10.1109/ICPR.2002.1048230", "http://doi.ieeecomputersociety.org/10.1109/ICPR.2002.1048230"],
	"pages": "36-39",
	"title": "Dependence Characteristics of Face Recognition Algorithms",
	"type": "inproceedings",
	"url": "db/conf/icpr/icpr2002-2.html#RukhinGPLHN02",
	"year": "2002"
}
