{
	"author": ["Roxana Geambasu", "Amit A. Levy", "Tadayoshi Kohno", "Arvind Krishnamurthy", "Henry M. Levy"],
	"booktitle": "OSDI",
	"crossref": "conf/osdi/2010",
	"dblpkey": "conf/osdi/GeambasuLKKL10",
	"ee": "http://www.usenix.org/events/osdi10/tech/full_papers/Geambasu.pdf",
	"pages": "323-336",
	"publisher": "USENIX Association",
	"stemmed": ["comet", "an", "activ", "distribut", "key", "valu", "store"],
	"tag": ["distributed", "named"],
	"title": "Comet: An active distributed key-value store",
	"type": "inproceedings",
	"venue": "OSDI",
	"year": 2010
}