{
	"author": ["J. Eliot B. Moss", "Ralf Johnson", "Alan Snyder", "David W. Stemple", "David Ungar"],
	"booktitle": "Proceedings of the Fourth Conference on Object-Oriented Programming: Systems, Languages, and Applications",
	"booktitleshort": "OOPSLA",
	"crossref": "conf/oopsla/1989",
	"dblpkey": "conf/oopsla/MossJSSU89",
	"editor": "George Bosworth",
	"isbn": "0-89791-333-7",
	"pages": "486-490",
	"publisher": "ACM",
	"tag": ["inheritance", "question"],
	"title": "Panel: Inheritance: Can We Have Our Cake and Eat it, Too?",
	"type": "inproceedings",
	"venue": "OOPSLA",
	"year": 1989
}