{
	"author": ["Yingqiang Lin", "Bir Bhanu"],
	"booktitle": "ICPR (3)",
	"booktitleshort": "ICPR v3",
	"crossref": "conf/icpr/2002",
	"dblpkey": "conf/icpr/LinB02",
	"doi": "10.1109/ICPR.2002.1047862",
	"ee": ["http://dx.doi.org/10.1109/ICPR.2002.1047862", "http://doi.ieeecomputersociety.org/10.1109/ICPR.2002.1047862"],
	"pages": "339-342",
	"publisher": "IEEE Computer Society",
	"publishershort": "IEEE CS",
	"stemmed": ["discov", "oper", "featur", "object", "detect"],
	"tag": ["detection"],
	"title": "Discovering Operators and Features for Object Detection",
	"type": "inproceedings",
	"venue": "ICPR",
	"year": 2002
}