{
	"author": ["Takahiro Hanyu", "Daisuke Suzuki", "Naoya Onizawa", "Masanori Natsui"],
	"booktitle": "DATE",
	"crossref": "conf/date/2017",
	"dblpkey": "conf/date/HanyuSON17",
	"ee": ["https://doi.org/10.23919/DATE.2017.7927048", "http://dl.acm.org/citation.cfm?id=3130504"],
	"pages": "548-553",
	"title": "Three-terminal MTJ-based nonvolatile logic circuits with self-terminated writing mechanism for ultra-low-power VLSI processor",
	"type": "inproceedings",
	"url": "db/conf/date/date2017.html#HanyuSON17",
	"year": "2017"
}
