{
	"author": ["Qing Xie", "Atif M. Memon"],
	"booktitle": "Proceedings of the 21st International Conference on Software Maintenance",
	"booktitleshort": "ICSM",
	"crossref": "conf/icsm/2005",
	"dblpkey": "conf/icsm/XieM05",
	"doi": "10.1109/ICSM.2005.72",
	"ee": "http://doi.ieeecomputersociety.org/10.1109/ICSM.2005.72",
	"isbn": "0-7695-2368-4",
	"pages": "473-482",
	"publisher": "IEEE Computer Society",
	"publishershort": "IEEE CS",
	"stemmed": ["rapid", "crash", "test", "continu", "evolv", "gui", "base", "softwar", "applic"],
	"tag": ["agile", "evolution", "testing"],
	"title": "Rapid “Crash Testing” for Continuously Evolving GUI-Based Software Applications",
	"type": "inproceedings",
	"venue": "ICSME",
	"year": 2005
}