{
	"author": ["Christopher York", "Clifford E. Wulfman", "Gregory R. Crane"],
	"booktitle": "Proceedings of the Seventh European Conference on Research and Advanced Technology for Digital Libraries",
	"booktitleshort": "ECDL",
	"crossref": "conf/ercimdl/2003",
	"dblpkey": "conf/ercimdl/YorkWC03",
	"doi": "10.1007/978-3-540-45175-4_18",
	"pages": "188-193",
	"publisher": "Springer",
	"series": "Lecture Notes in Computer Science",
	"seriesshort": "LNCS",
	"stemmed": ["structur", "awar", "queri", "for", "digit", "librari", "use", "case", "and", "challeng", "for", "the", "human"],
	"tag": ["case study", "challenge", "library", "query"],
	"title": "Structure-Aware Query for Digital Libraries: Use Cases and Challenges for the Humanities",
	"type": "inproceedings",
	"venue": "TPDL",
	"volume": 2769,
	"year": 2003
}