{
	"author": ["Hui Chao", "Daniel Tretter", "Xuemei Zhang", "Clayton Brian Atkins"],
	"booktitle": "Proceedings of the 10th Symposium on Document Engineering",
	"booktitleshort": "ACM Symposium on Document Engineering",
	"crossref": "conf/doceng/2010",
	"dblpkey": "conf/doceng/ChaoTZA10",
	"doi": "10.1145/1860559.1860582",
	"pages": "111-114",
	"publisher": "ACM",
	"stemmed": ["block", "recurs", "imag", "composit", "with", "exclus", "zone"],
	"tag": ["composition", "image", "recursion"],
	"title": "Blocked recursive image composition with exclusion zones",
	"type": "inproceedings",
	"venue": "DocEng",
	"year": 2010
}
