{
	"author": ["Stefan Schupp", "Erika Ábrahám"],
	"booktitle": "Proceedings of the 24th International Conference on Tools and Algorithms for the Construction and Analysis of Systems, Part II",
	"booktitleshort": "TACAS (2)",
	"crossref": "conf/tacas/2018-2",
	"dblpkey": "conf/tacas/SchuppA18",
	"doi": "10.1007/978-3-319-89963-3_17",
	"isbn": ["978-3-319-89962-6", "978-3-319-89963-3"],
	"pages": "287-302",
	"publisher": "Springer",
	"title": "Efficient Dynamic Error Reduction for Hybrid Systems Reachability Analysis",
	"type": "inproceedings",
	"venue": "TACAS",
	"year": 2018
}