{
	"author": ["Habib M. Fardoun", "Daniyal M. Alghazzawi", "Antonio Paules Ciprés", "Sebastián Romero López"],
	"booktitle": "HCI (15)",
	"crossref": "conf/hci/2014-15",
	"dblpkey": "conf/hci/FardounACL14",
	"doi": "10.1007/978-3-319-07485-6_39",
	"ee": "http://dx.doi.org/10.1007/978-3-319-07485-6_39",
	"pages": "397-407",
	"publisher": "Springer International Publishing",
	"publishershort": "Springer",
	"series": "Lecture Notes in Computer Science",
	"seriesshort": "LNCS",
	"stemmed": ["new", "way", "communiti", "servic", "communic", "administr"],
	"tag": ["communication", "community"],
	"title": "A New Way to Community Services — Communication with Administration",
	"type": "inproceedings",
	"venue": "HCI",
	"volume": 8524,
	"year": 2014
}