{
	"author": "Hélène Touzet",
	"booktitle": "ICALP",
	"crossref": "conf/icalp/1998",
	"dblpkey": "conf/icalp/Touzet98",
	"doi": "10.1007/BFb0055079",
	"ee": "http://dx.doi.org/10.1007/BFb0055079",
	"pages": "507-517",
	"publisher": "Springer-Verlag",
	"publishershort": "Springer",
	"series": "Lecture Notes in Computer Science",
	"seriesshort": "LNCS",
	"tag": ["term rewriting"],
	"title": "A Complex Example of a Simplifying Rewrite System",
	"type": "inproceedings",
	"venue": "ICALP",
	"volume": 1443,
	"year": 1998
}