{
	"author": ["Neema Moraveji", "Kori Inkpen", "Ed Cutrell", "Ravin Balakrishnan"],
	"booktitle": "Proceedings of the 27th ACM SIGCHI Conference on Human Factors in Computing Systems",
	"booktitleshort": "CHI",
	"crossref": "conf/chi/2009",
	"dblpkey": "conf/chi/MoravejiICB09",
	"doi": "10.1145/1518701.1519030",
	"isbn": "978-1-60558-246-7",
	"pages": "2157-2166",
	"publisher": "ACM",
	"stemmed": ["a", "mischief", "of", "mice", "examin", "children", "s", "perform", "in", "singl", "display", "groupwar", "system", "with", "to", "mice"],
	"tag": ["performance"],
	"title": "A mischief of mice: examining children’s performance in single display groupware systems with 1 to 32 mice",
	"type": "inproceedings",
	"venue": "CHI",
	"year": 2009
}