{
	"author": ["R. Ian Bull", "Jean-Marie Favre"]
	"booktitle": "MDDAUI '05, Model Driven Development of Advanced User Interfaces 2005, Proceedings of the MoDELS'05 Workshop on Model Driven Development of Advanced User Interfaces, Montego Bay, Jamaica, October 2, 2005"
	"booktitleshort": "MDDAUI"
	"crossref": "conf/uml/2005md"
	"dblpkey": "conf/uml/BullF05"
	"editor": ["Andreas Pleuß", "Jan Van den Bergh", "Heinrich Hußmann", "Stefan Sauer"]
	"ee": "http://www.ceur-ws.org/Vol-159/paper8.pdf"
	"publisher": "CEUR-WS.org"
	"series": "CEUR Workshop Proceedings"
	"title": "Visualization in the Context of Model Driven Engineering"
	"type": "inproceedings"
	"venue": "UML"
	"volume": "159"
	"year": 2005
}