{
	"author": ["Robert Kleinberg", "S. Matthew Weinberg"],
	"booktitle": "Proceedings of the 44th Annual ACM Symposium on Theory of Computing",
	"booktitleshort": "STOC",
	"crossref": "conf/stoc/2012",
	"dblpkey": "conf/stoc/KleinbergW12",
	"doi": "10.1145/2213977.2213991",
	"ee": "http://doi.acm.org/10.1145/2213977.2213991",
	"pages": "123-136",
	"publisher": "ACM",
	"stemmed": ["matroid", "prophet", "inequ"],
	"title": "Matroid prophet inequalities",
	"type": "inproceedings",
	"venue": "STOC",
	"year": 2012
}