{
	"author": ["Christoph Lüth", "Neil Ghani"],
	"booktitle": "Proceedings of the Seventh International Conference on Functional Programming",
	"booktitleshort": "ICFP",
	"crossref": "conf/icfp/2002",
	"dblpkey": "conf/icfp/LuthG02",
	"doi": "10.1145/581478.581492",
	"editor": ["Mitchell Wand", "Simon L. Peyton Jones"],
	"ee": "http://doi.acm.org/10.1145/581478.581492",
	"isbn": "1-58113-487-8",
	"pages": "133-144",
	"publisher": "ACM",
	"tag": ["monad"],
	"title": "Composing monads using coproducts",
	"type": "inproceedings",
	"venue": "ICFP",
	"year": 2002
}