{
	"author": ["Stefano Caselli", "Monica Reggiani"],
	"booktitle": "Proceedings of the Seventh Euromicro Workshop on Parallel and Distributed Processing. PDP'99, University of Madeira, Funchal, Portugal, February 3-5, 1999",
	"booktitleshort": "PDP",
	"crossref": "conf/pdp/1999",
	"dblpkey": "conf/pdp/CaselliR99",
	"doi": "10.1109/EMPDP.1999.746692",
	"isbn": "0-7695-0059-5",
	"pages": "297-304",
	"publisher": "IEEE Computer Society",
	"stemmed": ["random", "motion", "plan", "on", "parallel", "and", "distribut", "architectur"],
	"tag": ["architecture", "distributed", "parallel", "random"],
	"title": "Randomized motion planning on parallel and distributed architectures",
	"type": "inproceedings",
	"venue": "PDP",
	"year": 1999
}