{
	"author": ["Pao-Ann Hsiung", "Trong-Yen Lee", "Sao-Jie Chen"],
	"booktitle": "Proceedings of the 24th International Conference on Technology of Object-Oriented Languages and Systems",
	"booktitleshort": "TOOLS Asia",
	"crossref": "conf/tools/24-1997",
	"dblpkey": "conf/tools/HsiungLC97",
	"doi": "10.1109/TOOLS.1997.713555",
	"isbn": "0-8186-8551-4",
	"pages": "284-293",
	"publisher": "IEEE Computer Society",
	"publishershort": "IEEE CS",
	"stemmed": ["object", "orient", "technolog", "transfer", "to", "multiprocessor", "system", "level", "synthesi"],
	"tag": ["multi", "object-oriented", "synthesis"],
	"title": "Object-Oriented Technology Transfer to Multiprocessor System-Level Synthesis",
	"type": "inproceedings",
	"venue": "TOOLS",
	"year": 1997
}