{
	"author": ["Florian Alt", "Alireza Sahami Shirazi", "Thomas Kubitza", "Albrecht Schmidt"],
	"booktitle": "Proceedings of the 31st ACM SIGCHI Conference on Human Factors in Computing Systems",
	"booktitleshort": "CHI",
	"crossref": "conf/chi/2013",
	"dblpkey": "conf/chi/AltSKS13",
	"doi": "10.1145/2470654.2466226",
	"pages": "1709-1718",
	"publisher": "ACM",
	"stemmed": ["interact", "techniqu", "for", "creat", "and", "exchang", "content", "with", "public", "display"],
	"tag": ["interactive"],
	"title": "Interaction techniques for creating and exchanging content with public displays",
	"type": "inproceedings",
	"venue": "CHI",
	"year": 2013
}
