{
	"author": ["Manivannan Arivazhagan", "Harish Srinivasan", "Sargur N. Srihari"],
	"booktitle": "DRR",
	"crossref": "conf/drr/2007",
	"dblpkey": "conf/drr/ArivazhaganSS07",
	"ee": "http://dx.doi.org/10.1117/12.704538",
	"publisher": "SPIE",
	"stemmed": ["a", "statist", "approach", "to", "line", "segment", "in", "handwritten", "document"],
	"tag": ["approach", "documentation", "segmentation", "statistics"],
	"title": "A statistical approach to line segmentation in handwritten documents",
	"type": "inproceedings",
	"url": "db/conf/drr/drr2007.html#ArivazhaganSS07",
	"year": 2007
}