{
	"type": "inproceedings",
	"dblpkey": "conf/sigsoft/LeS08",
	"venue": "SIGSOFT",
	"author": ["Wei Le", "Mary Lou Soffa"],
	"title": "Marple: a demand-driven path-sensitive buffer overflow detector",
	"booktitle": "Proceedings of the 16th International Symposium on Foundations of Software Engineering",
	"booktitleshort": "SIGSOFT FSE",
	"year": 2008,
	"editor": ["Mary Jean Harrold", "Gail C. Murphy"],
	"pages": "272--282",
	"ee": "http://doi.acm.org/10.1145/1453101.1453137",
	"crossref": "conf/sigsoft/2008",
	"publisher": "ACM",
	"isbn": "978-1-59593-995-1"
}