{
	"author": ["Jerzy Dabrowski", "Andrzej Pulka"],
	"booktitle": "DATE",
	"crossref": "conf/date/1999",
	"dblpkey": "conf/date/DabrowskiP99",
	"doi": "10.1109/DATE.1999.10007",
	"ee": "http://doi.ieeecomputersociety.org/10.1109/DATE.1999.10007",
	"pages": "790-791",
	"publisher": "IEEE Computer Society",
	"publishershort": "IEEE CS",
	"stemmed": ["experi", "with", "model", "of", "analog", "and", "mix", "a", "d", "system", "base", "on", "pwl", "techniqu"],
	"tag": ["case study", "modelling"],
	"title": "Experiences with Modeling of Analog and Mixed A/D Systems Based on PWL Technique",
	"type": "inproceedings",
	"venue": "DATE",
	"year": 1999
}