{
	"author": ["Douglas D. Nebert", "James Fullton"],
	"booktitle": "DL",
	"crossref": "conf/dl/95",
	"dblpkey": "conf/dl/NebertF95",
	"ee": "http://www.csdl.tamu.edu/DL95/papers/nebert/nebert.html",
	"stemmed": ["use", "of", "the", "i", "site", "z", "softwar", "to", "search", "and", "retriev", "spatial", "referenc", "data"],
	"title": "Use of the ISite Z39.50 Software to Search and Retrieve Spatially-referenced Data",
	"type": "inproceedings",
	"url": "db/conf/dl/dl95.html#NebertF95",
	"year": 1995
}