{
	"author": "Michele Lanza",
	"booktitle": "Proceedings of the Seventh International Working Conference on Mining Software Repositories",
	"booktitleshort": "MSR",
	"crossref": "conf/msr/2010",
	"dblpkey": "conf/msr/Lanza10",
	"doi": "10.1109/MSR.2010.5463361",
	"ee": "http://dx.doi.org/10.1109/MSR.2010.5463361",
	"publisher": "IEEE Computer Society",
	"publishershort": "IEEE CS",
	"stemmed": ["the", "visual", "termin"],
	"tag": ["visual notation"],
	"title": "The visual terminator",
	"type": "inproceedings",
	"venue": "MSR",
	"year": 2010
}