{
	"author": ["Guillermo Cortes Robles", "Giner Alor-Hernández", "Alberto A. Aguilar-Lasserre", "Rubén Posada-Gómez"],
	"booktitle": "HCI (10)",
	"crossref": "conf/hci/2009-10",
	"dblpkey": "conf/hci/RoblesAAP09",
	"ee": "http://dx.doi.org/10.1007/978-3-642-02806-9_22",
	"pages": "184-192",
	"publisher": "Springer",
	"series": "Lecture Notes in Computer Science",
	"title": "Accelerating the Knowledge Innovation Process",
	"type": "inproceedings",
	"url": "db/conf/hci/hci2009-10.html#RoblesAAP09",
	"venue": "HCI",
	"volume": 5619,
	"year": 2009
}