{
	"author": "Parth Gupta",
	"booktitle": "Proceedings of the 37th International ACM SIGIR Conference on Research and Development in Information Retrieval",
	"booktitleshort": "SIGIR",
	"crossref": "conf/sigir/2014",
	"dblpkey": "conf/sigir/Gupta14",
	"doi": "10.1145/2600428.2610380",
	"ee": "http://doi.acm.org/10.1145/2600428.2610380",
	"pages": 1279,
	"publisher": "ACM",
	"stemmed": ["model", "of", "term", "across", "script", "through", "autoencod"],
	"tag": ["modelling"],
	"title": "Modelling of terms across scripts through autoencoders",
	"type": "inproceedings",
	"venue": "SIGIR",
	"year": 2014
}