{
	"author": ["Nikhil Chavan Dafle", "Matthew T. Mason", "Harald Staab", "Gregory F. Rossano", "Alberto Rodriguez"],
	"booktitle": "Proceedings of the 11th International Conference on Automation Science and Engineering",
	"booktitleshort": "CASE",
	"crossref": "conf/case/2015",
	"dblpkey": "conf/case/DafleMSRR15",
	"doi": "10.1109/CoASE.2015.7294269",
	"isbn": "978-1-4673-8183-3",
	"pages": "1249-1255",
	"publisher": "IEEE",
	"stemmed": ["a", "two", "phase", "gripper", "to", "reorient", "and", "grasp"],
	"title": "A two-phase gripper to reorient and grasp",
	"type": "inproceedings",
	"venue": "CASE",
	"year": 2015
}