{
	"author": ["Divyakant Agrawal", "Amr El Abbadi"],
	"booktitle": "VLDB",
	"cite": ["journals/tse/AhamadA89", "conf/podc/AgrawalA89", "journals/ipl/AgrawalA90", "journals/dc/BernsteinG87", "conf/sosp/DavcevB85", "journals/csur/DavidsonG85", "journals/cacm/EswarranGLT76", "journals/tods/EagerS83", "conf/pods/AbbadiSC85", "journals/tods/AbbadiT89", "conf/sosp/Gifford79", "journals/tocs/Herlihy86", "journals/tods/Herlihy87", "conf/sigmod/JajodiaM87", "conf/icdcs/Kumar90", "journals/tocs/Maekawa85", "conf/podc/MahaneyS85", "conf/icde/ParisL88", "journals/tocs/SchlichtingS83"],
	"crossref": "conf/vldb/90",
	"dblpkey": "conf/vldb/AgrawalA90",
	"ee": "http://www.vldb.org/conf/1990/P243.PDF",
	"pages": "243-254",
	"publisher": "Morgan Kaufmann",
	"stemmed": ["the", "tree", "quorum", "protocol", "an", "effici", "approach", "for", "manag", "replic", "data"],
	"tag": ["approach", "performance", "protocol"],
	"title": "The Tree Quorum Protocol: An Efficient Approach for Managing Replicated Data",
	"type": "inproceedings",
	"venue": "VLDB",
	"year": 1990
}