{
	"author": ["Gilles Barthe", "Guillaume Dufay"],
	"booktitle": "Proceedings of the Seventh International Conference on Fundamental Approaches to Software Engineering",
	"crossref": "conf/fase/2004",
	"dblpkey": "conf/fase/BartheD04",
	"doi": "10.1007/978-3-540-24721-0_7",
	"ee": "http://dx.doi.org/10.1007/978-3-540-24721-0_7",
	"pages": "99-113",
	"tag": ["bytecode", "verification"],
	"title": "A Tool-Assisted Framework for Certified Bytecode Verification",
	"type": "inproceedings",
	"venue": "FASE",
	"year": 2004
}