{
	"author": ["Harald Vogt", "Aswin van den Berg", "Arend Freije"],
	"booktitle": "WAGA",
	"crossref": "conf/waga/1990",
	"dblpkey": "conf/waga/VogtBF90",
	"doi": "10.1007/3-540-53101-7_8",
	"ee": "http://dx.doi.org/10.1007/3-540-53101-7_8",
	"pages": "101-115",
	"publisher": "Springer-Verlag",
	"publishershort": "Springer",
	"series": "Lecture Notes in Computer Science",
	"seriesshort": "LNCS",
	"tag": ["agile", "attribute grammar", "development", "program transformation"],
	"title": "Rapid Development of a Program Transformation System with Attribute Grammars and Dynamic Transformations",
	"type": "inproceedings",
	"volume": 461,
	"year": 1990
}