{
	"author": ["P. Mark Pettovello", "Farshad Fotouhi"],
	"booktitle": "Proceedings of the 21st Symposium on Applied Computing",
	"booktitleshort": "SAC",
	"crossref": "conf/sac/2006",
	"dblpkey": "conf/sac/PettovelloF06",
	"doi": "10.1145/1141277.1141389",
	"editor": "Hisham Haddad",
	"ee": "http://doi.acm.org/10.1145/1141277.1141389",
	"isbn": "1-59593-108-2",
	"pages": "474-481",
	"publisher": "ACM",
	"stemmed": ["mtree", "xml", "xpath", "graph", "index"],
	"tag": ["graph", "named", "xml"],
	"title": "MTree: an XML XPath graph index",
	"type": "inproceedings",
	"venue": "SAC",
	"year": 2006
}