{
	"author": ["Javier Esparza", "Antonín Kucera", "Richard Mayr"],
	"booktitle": "LICS",
	"crossref": "conf/lics/2004",
	"dblpkey": "conf/lics/EsparzaKM04",
	"doi": "10.1109/LICS.2004.1319596",
	"ee": ["http://dx.doi.org/10.1109/LICS.2004.1319596", "http://doi.ieeecomputersociety.org/10.1109/LICS.2004.1319596"],
	"pages": "12-21",
	"publisher": "IEEE Computer Society",
	"publishershort": "IEEE CS",
	"stemmed": ["model", "check", "probabilist", "pushdown", "automata"],
	"tag": ["automaton", "model checking", "probability"],
	"title": "Model Checking Probabilistic Pushdown Automata",
	"type": "inproceedings",
	"venue": "LICS",
	"year": 2004
}