{
	"author": ["Michael Abbott", "Thorsten Altenkirch", "Neil Ghani", "Conor McBride"],
	"booktitle": "Proceedings of the Sixth International Conference on Typed Lambda Calculi and Applications",
	"booktitleshort": "TLCA",
	"crossref": "conf/tlca/2003",
	"dblpkey": "conf/tlca/AbbottAGM03",
	"doi": "10.1007/3-540-44904-3_2",
	"ee": "http://dx.doi.org/10.1007/3-540-44904-3_2",
	"isbn": "3-540-40332-9",
	"pages": "16-30",
	"publisher": "Springer International Publishing",
	"publishershort": "Springer",
	"series": "Lecture Notes in Computer Science",
	"seriesshort": "LNCS",
	"stemmed": ["deriv", "of", "contain"],
	"title": "Derivatives of Containers",
	"type": "inproceedings",
	"venue": "TLCA",
	"volume": 2701,
	"year": 2003
}