{
	"author": "Giancarlo Guizzardi",
	"booktitle": "CAiSE",
	"crossref": "conf/caise/2007",
	"dblpkey": "conf/caise/Guizzardi07",
	"ee": "http://dx.doi.org/10.1007/978-3-540-72988-4_2",
	"pages": "5-20",
	"publisher": "Springer International Publishing",
	"publishershort": "Springer",
	"series": "Lecture Notes in Computer Science",
	"seriesshort": "LNCS",
	"title": "Modal Aspects of Object Types and Part-Whole Relations and the de re/de dicto Distinction",
	"type": "inproceedings",
	"url": "db/conf/caise/caise2007.html#Guizzardi07",
	"venue": "CAiSE",
	"volume": 4495,
	"year": 2007
}