{
	"author": ["Daniel Guerreiro e Silva", "Bruno Teixeira de Abreu", "Mario Jino"],
	"booktitle": "ICST",
	"crossref": "conf/icst/2009",
	"dblpkey": "conf/icst/SilvaAJ09",
	"ee": ["http://dx.doi.org/10.1109/ICST.2009.47", "http://doi.ieeecomputersociety.org/10.1109/ICST.2009.47"],
	"pages": "289-298",
	"publisher": "IEEE Computer Society",
	"publishershort": "IEEE CS",
	"tag": ["estimation", "functional", "testing"],
	"title": "A Simple Approach for Estimation of Execution Effort of Functional Test Cases",
	"type": "inproceedings",
	"year": 2009
}