{
	"author": ["Naoki Tani", "Danushka Bollegala", "Naiwala P. Chandrasiri", "Keisuke Okamoto", "Kazunari Nawa", "Shuhei Iitsuka", "Yutaka Matsuo"],
	"booktitle": "Proceedings of the 20th ACM International Conference on Information and Knowledge Management",
	"booktitleshort": "CIKM",
	"crossref": "conf/cikm/2011",
	"dblpkey": "conf/cikm/TaniBCONIM11",
	"doi": "10.1145/2063576.2063909",
	"isbn": "978-1-4503-0717-8",
	"pages": "2137-2140",
	"publisher": "ACM",
	"stemmed": ["collabor", "exploratori", "search", "in", "real", "world", "context"],
	"tag": ["collaboration"],
	"title": "Collaborative exploratory search in real-world context",
	"type": "inproceedings",
	"venue": "CIKM",
	"year": 2011
}