{
	"author": ["Edoardo Ardizzone", "Marco La Cascia", "Vito Di Gesù", "Cesare Valenti"],
	"booktitle": "ICPR",
	"crossref": "conf/icpr/1996",
	"dblpkey": "conf/icpr/ArdizzoneCGV96",
	"ee": ["http://dx.doi.org/10.1109/ICPR.1996.546810", "http://doi.ieeecomputersociety.org/10.1109/ICPR.1996.546810"],
	"pages": "140-144",
	"publisher": "IEEE Computer Society",
	"publishershort": "IEEE CS",
	"title": "Content-based indexing of image and video databases by global and shape features",
	"type": "inproceedings",
	"venue": "ICPR",
	"year": 1996
}