{
	"author": ["V. Wiktor Marek", "Anil Nerode", "Jeffrey B. Remmel"],
	"booktitle": "Logic Programming, Proceedings of the Joint International Conference and Symposium on Logic Programming, JICSLP 1992, Washington, DC, USA, November 1992",
	"booktitleshort": "JICSLP",
	"crossref": "conf/iclp/1992",
	"dblpkey": "conf/iclp/MarekNR92",
	"pages": "446-460",
	"publisher": "MIT Press",
	"tag": ["logic programming", "modelling"],
	"title": "The Stable Models of a Predicate Logic Program",
	"type": "inproceedings",
	"venue": "ICLP",
	"year": 1992
}