{
	"author": ["Wyne Wyne Kywe", "Masashi Yoshida", "Kazuhito Murakami"],
	"booktitle": "ICPR (4)",
	"booktitleshort": "ICPR v4",
	"crossref": "conf/icpr/2006",
	"dblpkey": "conf/icpr/KyweYM06",
	"doi": "10.1109/ICPR.2006.406",
	"ee": ["http://dx.doi.org/10.1109/ICPR.2006.406", "http://doi.ieeecomputersociety.org/10.1109/ICPR.2006.406"],
	"pages": "570-573",
	"publisher": "IEEE Computer Society",
	"publishershort": "IEEE CS",
	"tag": ["using"],
	"title": "Contact Lens Extraction by Using Thermo-Vision",
	"type": "inproceedings",
	"venue": "ICPR",
	"year": 2006
}