{
	"author": [
		"Pengyi Zhang",
		"Lynne Plettenberg",
		"Judith L. Klavans",
		"Douglas W. Oard",
		"Dagobert Soergel"
	],
	"booktitle": "Proceedings of the Seventh Joint Conference on Digital Libraries",
	"booktitleshort": "JCDL",
	"crossref": "conf/jcdl/2007",
	"dblpkey": "conf/jcdl/ZhangPKOS07",
	"doi": "10.1145/1255175.1255199",
	"pages": "117-126",
	"publisher": "ACM",
	"stemmed": [
		"task",
		"base",
		"interact",
		"with",
		"an",
		"integr",
		"multilingu",
		"multimedia",
		"inform",
		"system",
		"a",
		"format",
		"evalu"
	],
	"tag": [
		"evaluation",
		"information management",
		"interactive",
		"multi"
	],
	"title": "Task-based interaction with an integrated multilingual, multimedia information system: a formative evaluation",
	"type": "inproceedings",
	"venue": "JCDL",
	"year": 2007
}