{
	"type": "inproceedings",
	"dblpkey": "conf/sigsoft/NaudziunieneBDDGP11",
	"venue": "SIGSOFT",
	"author": ["Daiva Naudziuniene", "Matko Botincan", "Dino Distefano", "Mike Dodds", "Radu Grigore", "Matthew J. Parkinson"],
	"title": "jStar-eclipse: an IDE for automated verification of Java programs",
	"booktitle": "Proceedings of the 19th Symposium on the Foundations of Software Engineering and the 13rd European Software Engineering Conference",
	"booktitleshort": "SIGSOFT FSE",
	"year": 2011,
	"editor": ["Tibor Gyimóthy", "Andreas Zeller"],
	"pages": "428--431",
	"ee": "http://doi.acm.org/10.1145/2025113.2025182",
	"crossref": "conf/sigsoft/2011",
	"publisher": "ACM",
	"isbn": "978-1-4503-0443-6"
}