{
	"author": ["Björn Carlson", "Seif Haridi", "Sverker Janson"],
	"booktitle": "Proceedings of the International Symposium on Logic Programming",
	"booktitleshort": "ILPS",
	"crossref": "conf/slp/1994",
	"dblpkey": "conf/slp/CarlsonHJ94",
	"pages": "521-535",
	"publisher": "MIT Press",
	"stemmed": ["akl", "fd", "a", "concurr", "languag", "for", "fd", "program"],
	"tag": ["concurrent", "programming"],
	"title": "AKL(FD) — A Concurrent Language for FD Programming",
	"type": "inproceedings",
	"venue": "ICLP",
	"year": 1994
}