{
	"author": ["Bastian Ristau", "Torsten Limberg", "Gerhard Fettweis"],
	"booktitle": "DATE",
	"crossref": "conf/date/2008",
	"dblpkey": "conf/date/RistauLF08",
	"doi": "10.1109/DATE.2008.4484910",
	"ee": "http://dx.doi.org/10.1109/DATE.2008.4484910",
	"pages": "780-783",
	"publisher": "IEEE",
	"stemmed": ["a", "map", "framework", "for", "guid", "design", "space", "explor", "of", "heterogen", "mp", "so", "cs"],
	"tag": ["design", "framework"],
	"title": "A Mapping Framework for Guided Design Space Exploration of Heterogeneous MP-SoCs",
	"type": "inproceedings",
	"venue": "DATE",
	"year": 2008
}