{
	"type": "inproceedings",
	"dblpkey": "conf/csmr/MendoF05",
	"venue": "CSMR",
	"author": ["Fernando Alonso Mendo", "Guy Fitzgerald"],
	"title": "A Preliminary Study of the Evolution of SMEs Web Sites in the UK",
	"booktitle": "Proceedings of the Ninth European Conference on Software Maintenance and Reengineering",
	"booktitleshort": "CSMR",
	"year": 2005,
	"pages": "375--384",
	"crossref": "conf/csmr/2005",
	"ee": "http://doi.ieeecomputersociety.org/10.1109/CSMR.2005.2",
	"publisher": "IEEE Computer Society",
	"publishershort": "IEEE",
	"isbn": "0-7695-2304-8"
}