{
	"author": ["Jorge Garcia", "Niki Martinel", "Gian Luca Foresti", "Alfredo Gardel", "Christian Micheloni"],
	"booktitle": "Proceedings of the 22nd International Conference on Pattern Recognition",
	"booktitleshort": "ICPR",
	"crossref": "conf/icpr/2014",
	"dblpkey": "conf/icpr/GarciaMFGM14",
	"doi": "10.1109/ICPR.2014.790",
	"ee": "http://dx.doi.org/10.1109/ICPR.2014.790",
	"pages": "4618-4623",
	"publisher": "IEEE",
	"stemmed": ["person", "orient", "and", "featur", "distanc", "boost", "re", "identif"],
	"tag": ["identification"],
	"title": "Person Orientation and Feature Distances Boost Re-identification",
	"type": "inproceedings",
	"venue": "ICPR",
	"year": 2014
}