{
	"author": ["Michelle Dominguez", "Matthew L. Bernacki", "Phillip Merlin Uesbeck"],
	"booktitle": "Proceedings of the Ninth International Conference on Educational Data Mining",
	"booktitleshort": "EDM",
	"crossref": "conf/edm/2016",
	"dblpkey": "conf/edm/DominguezBU16",
	"ee": "http://www.educationaldatamining.org/EDM2016/proceedings/paper_47.pdf",
	"pages": "589-590",
	"stemmed": ["predict", "stem", "achiev", "with", "learn", "manag", "system", "data", "predict", "model", "and", "a", "test", "of", "an", "earli", "warn", "system"],
	"tag": ["learning", "modelling", "predict"],
	"title": "Predicting STEM Achievement with Learning Management System Data: Prediction Modeling and a Test of an Early Warning System",
	"type": "inproceedings",
	"venue": "EDM",
	"year": 2016
}