{
	"author": ["Babak Bagheri Hariri", "Diego Calvanese", "Giuseppe De Giacomo", "Alin Deutsch", "Marco Montali"],
	"booktitle": "Proceedings of the 32nd Symposium on Principles of Database Systems",
	"booktitleshort": "PODS",
	"crossref": "conf/pods/2013",
	"dblpkey": "conf/pods/HaririCGDM13",
	"doi": "10.1145/2463664.2465221",
	"pages": "163-174",
	"publisher": "ACM",
	"stemmed": ["verif", "of", "relat", "data", "centric", "dynam", "system", "with", "extern", "servic"],
	"tag": ["relational", "verification"],
	"title": "Verification of relational data-centric dynamic systems with external services",
	"type": "inproceedings",
	"venue": "PODS",
	"year": 2013
}
