{
	"author": ["Premkumar T. Devanbu", "Brendan Murphy", "Nachiappan Nagappan", "Thomas Zimmermann", "Valentin Dallmeier"],
	"booktitle": "ISSTA",
	"crossref": "conf/issta/2008",
	"dblpkey": "conf/issta/DevanbuMNZD08",
	"doi": "10.1145/1390630.1390668",
	"ee": "http://doi.acm.org/10.1145/1390630.1390668",
	"pages": "307-308",
	"publisher": "ACM",
	"tag": ["fault", "scalability", "workshop"],
	"title": "DEFECTS 2008: international workshop on defects in large software systems",
	"type": "inproceedings",
	"venue": "ISSTA",
	"year": 2008
}