{
	"author": "Jessica Hammer",
	"booktitle": "Proceedings of the Fifth DiGRA International Conference: Breaking New Ground: Innovation in Games, Play, Practice and Theory",
	"booktitleshort": "DiGRA",
	"crossref": "conf/digra/2009",
	"dblpkey": "conf/digra/Hammer09",
	"ee": "http://www.digra.org/digital-library/publications/creativity-in-the-game-design-classroom/",
	"stemmed": ["creativ", "in", "the", "game", "design", "classroom"],
	"tag": ["design", "game studies"],
	"title": "Creativity in the Game Design Classroom",
	"type": "inproceedings",
	"venue": "DiGRA",
	"year": 2009
}