{
	"author": ["Pedro Alves Nogueira", "Rúben Aguiar", "Rui Amaral Rodrigues", "Eugénio C. Oliveira", "Lennart E. Nacke"],
	"booktitle": "Proceedings of the 10th Conference on Artificial Intelligence and Interactive Digital Entertainment",
	"booktitleshort": "AIIDE",
	"crossref": "conf/aiide/2014",
	"dblpkey": "conf/aiide/NogueiraARON14",
	"ee": "http://www.aaai.org/ocs/index.php/AIIDE/AIIDE14/paper/view/8947",
	"isbn": "978-1-57735-681-3",
	"publisher": "AAAI",
	"stemmed": ["fuzzi", "affect", "player", "model", "a", "physiolog", "base", "hierarch", "cluster", "method"],
	"tag": ["clustering", "fuzzy", "modelling"],
	"title": "Fuzzy Affective Player Models: A Physiology-Based Hierarchical Clustering Method",
	"type": "inproceedings",
	"venue": "AIIDE",
	"year": 2014
}