{
	"author": [
		"Giulia Pedrielli",
		"Arianna Alfieri",
		"Andrea Matta"
	],
	"booktitle": "Proceedings of the 10th International Conference on Automation Science and Engineering",
	"booktitleshort": "CASE",
	"crossref": "conf/case/2014",
	"dblpkey": "conf/case/PedrielliAM14",
	"doi": "10.1109/CoASE.2014.6899355",
	"ee": "http://dx.doi.org/10.1109/CoASE.2014.6899355",
	"pages": "393-398",
	"publisher": "IEEE",
	"stemmed": [
		"time",
		"buffer",
		"control",
		"system",
		"for",
		"multi",
		"stage",
		"product",
		"line"
	],
	"tag": [
		"multi"
	],
	"title": "Time Buffer Control System for multi-stage production lines",
	"type": "inproceedings",
	"venue": "CASE",
	"year": 2014
}