{
	"author": ["Benjamin Barrois", "Karthick Parashar", "Olivier Sentieys"],
	"booktitle": "Proceedings of the 20th Conference and Exhibition on Design, Automation and Test in Europe",
	"booktitleshort": "DATE",
	"crossref": "conf/date/2016",
	"dblpkey": "conf/date/BarroisPS16",
	"ee": "http://ieeexplore.ieee.org/document/7459407/",
	"isbn": "978-3-9815-3707-9",
	"pages": "750-755",
	"publisher": "IEEE",
	"tag": ["evaluation", "scalability"],
	"title": "Leveraging power spectral density for scalable system-level accuracy evaluation",
	"type": "inproceedings",
	"venue": "DATE",
	"year": 2016
}