{
	"author": ["Andrés Corrada-Emmanuel", "Howard J. Schultz"],
	"booktitle": "Proceedings of the 25th International Conference on Machine Learning",
	"booktitleshort": "ICML",
	"crossref": "conf/icml/2008",
	"dblpkey": "conf/icml/Corrada-EmmanuelS08",
	"doi": "10.1145/1390156.1390178",
	"isbn": "978-1-60558-205-4",
	"pages": "168-175",
	"publisher": "ACM",
	"series": "ACM International Conference Proceeding Series",
	"stemmed": ["autonom", "geometr", "precis", "error", "estim", "in", "low", "level", "comput", "vision", "task"],
	"tag": ["estimation", "fault", "geometry", "low level", "precise"],
	"title": "Autonomous geometric precision error estimation in low-level computer vision tasks",
	"type": "inproceedings",
	"venue": "ICML",
	"volume": 307,
	"year": 2008
}