{
	"author": ["Casper Bach Poulsen", "Peter D. Mosses", "Paolo Torrini"],
	"booktitle": "Proceedings of the 20th Workshop on Partial Evaluation and Program Manipulation",
	"crossref": "conf/pepm/2015",
	"dblpkey": "conf/pepm/PoulsenMT15",
	"doi": "10.1145/2678015.2682545",
	"ee": "http://doi.acm.org/10.1145/2678015.2682545",
	"pages": "3-8",
	"publisher": "ACM",
	"tag": ["abstract interpretation", "imperative", "polymorphism"],
	"title": "Imperative Polymorphism by Store-Based Types as Abstract Interpretations",
	"type": "inproceedings",
	"venue": "PEPM",
	"year": 2015
}