{
	"address": ["Amsterdam", "", "The Netherlands"],
	"dblpkey": "conf/wicsa/2001",
	"ee": "http://www.computer.org/csdl/proceedings/wicsa/2001/1360/00/index.html",
	"ieeepuid": 7539,
	"isbn": "0-7695-1360-3",
	"publisher": "IEEE Computer Society",
	"publishershort": "IEEE CS",
	"tagged": [["architecture", 15],
		["approach", 2],
		["named", 2],
		["object-oriented", 2],
		["product line", 2]],
	"title": "Proceedings of the Second Working IEEE / IFIP Conference on Software Architecture",
	"titleshort": "WICSA",
	"type": "proceedings",
	"venue": "WICSA",
	"year": 2001
}
