{
	"author": ["Chih-Yu Hsiao", "You-Jia Liu", "Mao-Jiun J. Wang"],
	"booktitle": "Proceedings of the 15th International Conference on Human Interface and the Management of Information. Part I: Information and Interaction Design",
	"booktitleshort": "HCI/HIMI p1",
	"crossref": "conf/hci/2013-13",
	"dblpkey": "conf/hci/HsiaoLW13",
	"doi": "10.1007/978-3-642-39209-2_6",
	"ee": "http://dx.doi.org/10.1007/978-3-642-39209-2_6",
	"pages": "48-54",
	"publisher": "Springer International Publishing",
	"publishershort": "Springer",
	"series": "Lecture Notes in Computer Science",
	"seriesshort": "LNCS",
	"stemmed": ["usabl", "evalu", "of", "the", "touch", "screen", "user", "interfac", "design"],
	"tag": ["design", "evaluation", "usability", "user interface"],
	"title": "Usability Evaluation of the Touch Screen User Interface Design",
	"type": "inproceedings",
	"venue": "HCI",
	"volume": 8016,
	"year": 2013
}