{
	"address": ["Paphos", "", "Cyprus"],
	"dblpkey": "conf/iceis/2006sp",
	"editor": ["Yannis Manolopoulos", "Joaquim Filipe", "Panos Constantopoulos", "José Cordeiro"],
	"isbn": "978-3-540-77580-5",
	"publisher": "Springer International Publishing",
	"publishershort": "Springer",
	"series": "Lecture Notes in Business Information Processing",
	"seriesshort": "LNBIP",
	"tagged": [["modelling", 5],
		["semantics", 5],
		["process", 4],
		["approach", 3],
		["framework", 3],
		["information management", 3],
		["web", 3],
		["collaboration", 2],
		["database", 2],
		["development", 2],
		["enterprise", 2],
		["on the", 2],
		["ontology", 2],
		["tool support", 2],
		["towards", 2],
		["visualisation", 2]],
	"title": "Revised Selected Papers of the Eighth International Conference on Enterprise Information Systems",
	"titleshort": "Post-ICEIS",
	"type": "proceedings",
	"venue": "ICEIS",
	"volume": 3,
	"year": 2006
}
