{
	"author": ["Pedro Valente", "David Aveiro", "Nuno Jardim Nunes"],
	"booktitle": "ICEIS (2)",
	"booktitleshort": "ICEIS v2",
	"crossref": "conf/iceis/2015-2",
	"dblpkey": "conf/iceis/ValenteAN15",
	"doi": "10.5220/0005383803880394",
	"ee": "http://dx.doi.org/10.5220/0005383803880394",
	"pages": "388-394",
	"publisher": "SciTePress",
	"stemmed": ["improv", "softwar", "design", "decis", "toward", "enhanc", "return", "of", "invest"],
	"tag": ["design", "towards"],
	"title": "Improving Software Design Decisions towards Enhanced Return of Investment",
	"type": "inproceedings",
	"venue": "ICEIS",
	"year": 2015
}