{
	"author": "Lionel C. Briand",
	"booktitle": "Proceedings of the 13th Working Conference on Reverse Engineering",
	"booktitleshort": "WCRE",
	"crossref": "conf/wcre/2006",
	"dblpkey": "conf/wcre/Briand06",
	"ee": "http://doi.ieeecomputersociety.org/10.1109/WCRE.2006.53",
	"isbn": "0-7695-2719-1",
	"pages": "3--8",
	"publisher": "IEEE Computer Society",
	"publishershort": "IEEE",
	"title": "The Experimental Paradigm in Reverse Engineering: Role, Challenges, and Limitations",
	"type": "inproceedings",
	"venue": "WCRE",
	"year": 2006
}