{
	"author": ["Marco Montali", "Paolo Torroni", "Marco Alberti", "Federico Chesani", "Marco Gavanelli", "Evelina Lamma", "Paola Mello"],
	"booktitle": "ICLP",
	"crossref": "conf/iclp/2008",
	"dblpkey": "conf/iclp/MontaliTACGLM08",
	"doi": "10.1007/978-3-540-89982-2_39",
	"ee": "http://dx.doi.org/10.1007/978-3-540-89982-2_39",
	"pages": "440-454",
	"tag": ["declarative", "logic programming", "specification", "verification"],
	"title": "Verification from Declarative Specifications Using Logic Programming",
	"type": "inproceedings",
	"year": 2008
}