{
	"author": ["F. Wai-ling Ho-Ching", "Jennifer Mankoff", "James A. Landay"],
	"booktitle": "Proceedings of the 21st ACM SIGCHI Conference on Human Factors in Computing Systems",
	"booktitleshort": "CHI",
	"crossref": "conf/chi/2003",
	"dblpkey": "conf/chi/Ho-ChingML03",
	"doi": "10.1145/642611.642641",
	"isbn": "1-58113-630-7",
	"pages": "161-168",
	"publisher": "ACM",
	"stemmed": ["can", "you", "see", "what", "i", "hear", "the", "design", "and", "evalu", "of", "a", "peripher", "sound", "display", "for", "the", "deaf"],
	"tag": ["design", "evaluation", "what"],
	"title": "Can you see what i hear?: the design and evaluation of a peripheral sound display for the deaf",
	"type": "inproceedings",
	"venue": "CHI",
	"year": 2003
}