{
	"type": "inproceedings",
	"dblpkey": "conf/popl/JonesM82",
	"venue": "POPL",
	"author": ["Neil D. Jones", "Steven S. Muchnick"],
	"title": "A Flexible Approach to Interprocedural Data Flow Analysis and Programs with Recursive Data Structures",
	"booktitle": "Conference Record of the Ninth Annual Symposium on Principles of Programming Languages",
	"booktitleshort": "POPL",
	"year": 1982,
	"editor": "Richard A. DeMillo",
	"pages": "66--74",
	"crossref": "conf/popl/82",
	"cdrom": "POPL/00001532.PDF",
	"ee": "http://doi.acm.org/10.1145/582153.582161",
	"publisher": "ACM Press",
	"isbn": "0-89791-065-6"
}