{
	"author": [
		"Enric Pastor",
		"Jordi Cortadella"
	],
	"booktitle": "Proceedings of the Third Conference on Design, Automation and Test in Europe",
	"booktitleshort": "DATE",
	"crossref": "conf/date/1998",
	"dblpkey": "conf/date/PastorC98",
	"doi": "10.1109/DATE.1998.655948",
	"ee": "http://doi.ieeecomputersociety.org/10.1109/DATE.1998.655948",
	"pages": "790-795",
	"publisher": "IEEE Computer Society",
	"publishershort": "IEEE CS",
	"stemmed": [
		"effici",
		"encod",
		"scheme",
		"for",
		"symbol",
		"analysi",
		"of",
		"petri",
		"net"
	],
	"tag": [
		"analysis",
		"encoding",
		"performance",
		"petri net"
	],
	"title": "Efficient Encoding Schemes for Symbolic Analysis of Petri Nets",
	"type": "inproceedings",
	"venue": "DATE",
	"year": 1998
}