{
	"author": ["Sungsoo Yoon", "Seung-Seok Choi", "Sung-Hyuk Cha", "Charles C. Tappert"],
	"booktitle": "ICDAR",
	"crossref": "conf/icdar/2005",
	"dblpkey": "conf/icdar/YoonCCT05",
	"ee": ["http://dx.doi.org/10.1109/ICDAR.2005.256", "http://doi.ieeecomputersociety.org/10.1109/ICDAR.2005.256"],
	"pages": 600,
	"publisher": "IEEE Computer Society",
	"stemmed": ["writer", "profil", "use", "handwrit", "copybook", "style"],
	"tag": ["profiling", "using"],
	"title": "Writer Profiling Using Handwriting Copybook Styles",
	"type": "inproceedings",
	"url": "db/conf/icdar/icdar2005.html#YoonCCT05",
	"year": 2005
}