{
	"author": "Gang Wang",
	"booktitle": "SEKE",
	"crossref": "conf/seke/2014",
	"dblpkey": "conf/seke/Wang14",
	"pages": "361-364",
	"publisher": "Knowledge Systems Institute Graduate School",
	"stemmed": ["qos", "base", "web", "servic", "composit", "by", "ga", "use", "consum", "decis", "make", "function"],
	"tag": ["composition", "using", "web", "web service"],
	"title": "QoS-Based Web Service Composition by GA Using Consumer Decision-Making Function",
	"type": "inproceedings",
	"venue": "SEKE",
	"year": 2014
}