{
	"author": ["Rosane S. Huergo", "Paulo F. Pires", "Flávia Coimbra Delicato"],
	"booktitle": "Proceedings of the 29th Symposium on Applied Computing",
	"booktitleshort": "SAC",
	"crossref": "conf/sac/2014",
	"dblpkey": "conf/sac/HuergoPD14",
	"doi": "10.1145/2554850.2554973",
	"editor": ["Yookun Cho", "Sung Y. Shin", "Sang-Wook Kim", "Chih-Cheng Hung", "Jiman Hong"],
	"ee": "http://doi.acm.org/10.1145/2554850.2554973",
	"isbn": "978-1-4503-2469-4",
	"pages": "1225-1230",
	"publisher": "ACM",
	"stemmed": ["method", "identifi", "servic", "use", "master", "data", "artifact", "centric", "model", "approach"],
	"tag": ["approach", "identification", "modelling", "using"],
	"title": "A method to identify services using master data and artifact-centric modeling approach",
	"type": "inproceedings",
	"venue": "SAC",
	"year": 2014
}