{
	"author": "Brad Adelberg",
	"booktitle": "SIGMOD Conference",
	"cdrom": "SIGMOD98/P283.PDF",
	"cite": ["conf/icdt/Abiteboul97", "...", "...", "journals/sigmod/AshishK97", "conf/ipsj/ChawatheGHPUW94", "...", "...", "...", "...", "..."],
	"crossref": "conf/sigmod/98",
	"dblpkey": "conf/sigmod/Adelberg98",
	"ee": "http://doi.acm.org/10.1145/276304.276330",
	"pages": "283-294",
	"stemmed": ["no", "do", "se", "a", "tool", "for", "semi", "automat", "extract", "semi", "structur", "data", "from", "text", "document"],
	"title": "NoDoSE — A Tool for Semi-Automatically Extracting Semi-Structured Data from Text Documents",
	"type": "inproceedings",
	"url": "db/conf/sigmod/sigmod98.html#Adelberg98",
	"year": 1998
}