{
	"author": ["Sean Seefried", "Manuel M. T. Chakravarty", "Gabriele Keller"],
	"booktitle": "Proceedings of the Third International Conference on Generative Programming and Component Engineering",
	"booktitleshort": "GPCE",
	"crossref": "conf/gpce/2004",
	"dblpkey": "conf/gpce/SeefriedCK04",
	"doi": "10.1007/978-3-540-30175-2_10",
	"ee": "http://dx.doi.org/10.1007/978-3-540-30175-2_10",
	"pages": "186-205",
	"publisher": "Springer International Publishing",
	"publishershort": "Springer",
	"series": "Lecture Notes in Computer Science",
	"seriesshort": "LNCS",
	"tag": ["domain-specific language", "embedded", "haskell", "optimisation", "using"],
	"title": "Optimising Embedded DSLs Using Template Haskell",
	"type": "inproceedings",
	"venue": "GPCE",
	"volume": 3286,
	"year": 2004
}