{
	"author": ["John Colgrove", "John D. Davis", "John Hayes", "Ethan L. Miller", "Cary Sandvig", "Russell Sears", "Ari Tamches", "Neil Vachharajani", "Feng Wang"],
	"booktitle": "Proceedings of the 33rd ACM SIGMOD International Conference on Management of Data",
	"booktitleshort": "SIGMOD",
	"crossref": "conf/sigmod/2015",
	"dblpkey": "conf/sigmod/ColgroveDHMSSTV15",
	"doi": "10.1145/2723372.2742798",
	"isbn": "978-1-4503-2758-9",
	"pages": "1683-1694",
	"publisher": "ACM",
	"stemmed": ["puriti", "build", "fast", "high", "avail", "enterpris", "flash", "storag", "from", "commod", "compon"],
	"tag": ["component", "enterprise", "named", "performance"],
	"title": "Purity: Building Fast, Highly-Available Enterprise Flash Storage from Commodity Components",
	"type": "inproceedings",
	"venue": "SIGMOD",
	"year": 2015
}