{
	"author": ["Michael Eagle", "Vinaya Polamreddi", "Behrooz Mostafavi", "Tiffany Barnes"],
	"booktitle": "Proceedings of the Seventh International Conference on Educational Data Mining",
	"booktitleshort": "EDM",
	"crossref": "conf/edm/2014",
	"dblpkey": "conf/edm/EaglePMB14",
	"ee": "http://www.educationaldatamining.org/EDM2014/uploads/procs2014/shortpapers/249_EDM-2014-Short.pdf",
	"pages": "249-252",
	"title": "Exploration of Student's Use of Rule Application References in a Propositional Logic Tutor",
	"type": "inproceedings",
	"venue": "EDM",
	"year": 2014
}