{
	"booktitle": "CGO",
	"dblpkey": "conf/cgo/2009",
	"ee": ["http://ieeexplore.ieee.org/xpl/mostRecentIssue.jsp?punumber=4907622", "http://www.computer.org/csdl/proceedings/cgo/2009/3576/00/index.html", "http://dl.acm.org/citation.cfm?id=1545006"],
	"isbn": "978-0-7695-3576-0",
	"publisher": "IEEE Computer Society",
	"title": "Proceedings of the CGO 2009, The Seventh International Symposium on Code Generation and Optimization, Seattle, Washington, USA, March 22-25, 2009",
	"type": "proceedings",
	"url": "db/conf/cgo/cgo2009.html",
	"year": "2009"
}
